qmeasure_jupyter/__init__.py
qmeasure_jupyter/_version.py
qmeasure_jupyter-1.0.0.data/data/share/jupyter/labextensions/qmeasure-jupyter/package.json
qmeasure_jupyter-1.0.0.data/data/share/jupyter/labextensions/qmeasure-jupyter/schemas/qmeasure-jupyter/package.json.orig
qmeasure_jupyter-1.0.0.data/data/share/jupyter/labextensions/qmeasure-jupyter/static/17382e1a69bd628107e8.wasm
qmeasure_jupyter-1.0.0.data/data/share/jupyter/labextensions/qmeasure-jupyter/static/181.d9bc57279a6bfe9019cf.js
qmeasure_jupyter-1.0.0.data/data/share/jupyter/labextensions/qmeasure-jupyter/static/805.e6dfa5a942102624a93d.js
qmeasure_jupyter-1.0.0.data/data/share/jupyter/labextensions/qmeasure-jupyter/static/812.a5d8eddcc181fa5cffb5.js
qmeasure_jupyter-1.0.0.data/data/share/jupyter/labextensions/qmeasure-jupyter/static/8c93692fb368e288a582.wasm
qmeasure_jupyter-1.0.0.data/data/share/jupyter/labextensions/qmeasure-jupyter/static/932.c64d09d388404218b9af.js
qmeasure_jupyter-1.0.0.data/data/share/jupyter/labextensions/qmeasure-jupyter/static/remoteEntry.b25e8c0f4e818867b33b.js
qmeasure_jupyter-1.0.0.data/data/share/jupyter/labextensions/qmeasure-jupyter/static/style.js
qmeasure_jupyter-1.0.0.data/data/share/jupyter/labextensions/qmeasure-jupyter/static/third-party-licenses.json
qmeasure_jupyter-1.0.0.data/data/share/jupyter/labextensions/qmeasure-jupyter/install.json
qmeasure_jupyter-1.0.0.dist-info/METADATA
qmeasure_jupyter-1.0.0.dist-info/WHEEL
qmeasure_jupyter-1.0.0.dist-info/licenses/LICENSE
qmeasure_jupyter-1.0.0.dist-info/RECORD
