Metadata-Version: 2.4
Name: qmeasure_jupyter
Version: 1.0.0
Dynamic: Keywords
Summary: JupyterLab extension for QMeasure/MeasureIt sweep management
Project-URL: Homepage, https://github.com/caidish/qmeasure-jupyter
Project-URL: Bug Tracker, https://github.com/caidish/qmeasure-jupyter/issues
Project-URL: Repository, https://github.com/caidish/qmeasure-jupyter.git
Author-email: "QMeasure Contributors: Jiaqi caidish" <jiaqic@mit.edu>
License: MIT License
License-File: LICENSE
Classifier: Framework :: Jupyter
Classifier: Framework :: Jupyter :: JupyterLab
Classifier: Framework :: Jupyter :: JupyterLab :: 4
Classifier: Framework :: Jupyter :: JupyterLab :: Extensions
Classifier: Framework :: Jupyter :: JupyterLab :: Extensions :: Prebuilt
Classifier: License :: OSI Approved :: MIT License
Classifier: Programming Language :: Python
Classifier: Programming Language :: Python :: 3
Classifier: Programming Language :: Python :: 3.8
Classifier: Programming Language :: Python :: 3.9
Classifier: Programming Language :: Python :: 3.10
Classifier: Programming Language :: Python :: 3.11
Classifier: Programming Language :: Python :: 3.12
Requires-Python: >=3.8
Requires-Dist: jupyterlab<5,>=4.0.0
Provides-Extra: dev
Requires-Dist: pytest-cov; extra == 'dev'
Requires-Dist: pytest>=7.0; extra == 'dev'
Requires-Dist: qmeasure>=1.1.0; extra == 'dev'
